asyncdns.py
common.py
daemon.py
encrypt.py
eventloop.py
local.py
lru_cache.py
manager.py
server.py
shell.py
tcprelay.py
udprelay.py
crypto/__init__.py
crypto/openssl.py
crypto/rc4_md5.py
crypto/sodium.py
crypto/table.py
crypto/util.py
bsn_ss_new-0.1.1.dist-info/METADATA
bsn_ss_new-0.1.1.dist-info/WHEEL
bsn_ss_new-0.1.1.dist-info/entry_points.txt
bsn_ss_new-0.1.1.dist-info/top_level.txt
bsn_ss_new-0.1.1.dist-info/RECORD
