Metadata-Version: 2.4
Name: bsn-ss-new
Version: 0.1.1
Summary: A modified Shadowsocks package
Home-page: https://github.com/your_github_username/bsn-ss-new
Author: Your Name
Author-email: your.email@example.com
Classifier: Programming Language :: Python :: 3
Classifier: License :: OSI Approved :: MIT License
Classifier: Operating System :: OS Independent
Classifier: Topic :: Internet :: Proxy Servers
Classifier: Topic :: Security :: Cryptography
Requires-Python: >=3.7
Requires-Dist: pycryptodome>=3.8.0
Requires-Dist: blinker>=1.4
Requires-Dist: dnspython>=1.15.0
Dynamic: author
Dynamic: author-email
Dynamic: classifier
Dynamic: description
Dynamic: description-content-type
Dynamic: home-page
Dynamic: requires-dist
Dynamic: requires-python
Dynamic: summary
